rankvectors/__init__.py
rankvectors/api_client.py
rankvectors/api_response.py
rankvectors/configuration.py
rankvectors/exceptions.py
rankvectors/py.typed
rankvectors/rest.py
rankvectors/api/__init__.py
rankvectors/api/analytics_api.py
rankvectors/api/api_keys_api.py
rankvectors/api/content_verification_api.py
rankvectors/api/crawling_api.py
rankvectors/api/implementations_api.py
rankvectors/api/pages_api.py
rankvectors/api/projects_api.py
rankvectors/api/suggestions_api.py
rankvectors/api/user_api.py
rankvectors/api/webhooks_api.py
rankvectors/com/__init__.py
rankvectors/com/rankvectors/__init__.py
rankvectors/com/rankvectors/api/__init__.py
rankvectors/com/rankvectors/api/analytics_api.py
rankvectors/com/rankvectors/api/api_keys_api.py
rankvectors/com/rankvectors/api/content_verification_api.py
rankvectors/com/rankvectors/api/crawling_api.py
rankvectors/com/rankvectors/api/credits_api.py
rankvectors/com/rankvectors/api/implementations_api.py
rankvectors/com/rankvectors/api/pages_api.py
rankvectors/com/rankvectors/api/projects_api.py
rankvectors/com/rankvectors/api/suggestions_api.py
rankvectors/com/rankvectors/api/user_api.py
rankvectors/com/rankvectors/api/webhooks_api.py
rankvectors/com/rankvectors/model/__init__.py
rankvectors/com/rankvectors/model/add_credits200_response.py
rankvectors/com/rankvectors/model/add_credits_request.py
rankvectors/com/rankvectors/model/api_key.py
rankvectors/com/rankvectors/model/api_key_response.py
rankvectors/com/rankvectors/model/auto_recharge_settings.py
rankvectors/com/rankvectors/model/batch_sync_pages200_response.py
rankvectors/com/rankvectors/model/batch_sync_pages_request.py
rankvectors/com/rankvectors/model/change_result.py
rankvectors/com/rankvectors/model/content_verification.py
rankvectors/com/rankvectors/model/crawl.py
rankvectors/com/rankvectors/model/create_api_key_request.py
rankvectors/com/rankvectors/model/create_project_request.py
rankvectors/com/rankvectors/model/credit_balance.py
rankvectors-1.3.1.dist-info/METADATA
rankvectors-1.3.1.dist-info/WHEEL
rankvectors-1.3.1.dist-info/top_level.txt
rankvectors-1.3.1.dist-info/RECORD
