Metadata-Version: 2.4
Name: rankvectors
Version: 1.3.1
Summary: RankVectors API
Home-page: 
Author: RankVectors Support
Author-email: RankVectors Support <tj@rankvectors.com>
License: MIT
Project-URL: Repository, https://github.com/rankvectors/rankvectors-python-sdk
Keywords: OpenAPI,OpenAPI-Generator,RankVectors API
Requires-Python: >=3.9
Requires-Dist: urllib3<3.0.0,>=2.1.0
Requires-Dist: python-dateutil>=2.8.2
Requires-Dist: pydantic>=2
Requires-Dist: typing-extensions>=4.7.1
Dynamic: author
